licensing/__init__.c
licensing/__init__.cpython-39-darwin.so
licensing/_static_version.py
licensing/_version.py
licensing/activation.c
licensing/activation.cpython-39-darwin.so
licensing/server_communications.c
licensing/server_communications.cpython-39-darwin.so
licensing/utils.c
licensing/utils.cpython-39-darwin.so
licensing/dummy_scqt/__init__.c
licensing/dummy_scqt/__init__.cpython-39-darwin.so
licensing/validation/__init__.c
licensing/validation/__init__.cpython-39-darwin.so
licensing/validation/database_validation.c
licensing/validation/database_validation.cpython-39-darwin.so
licensing/validation/license_file_validation.c
licensing/validation/license_file_validation.cpython-39-darwin.so
oqs_licensing-1.0.12.dist-info/METADATA
oqs_licensing-1.0.12.dist-info/WHEEL
oqs_licensing-1.0.12.dist-info/top_level.txt
oqs_licensing-1.0.12.dist-info/RECORD
