Metadata-Version: 2.1
Name: oqs-licensing
Version: 1.0.12
Summary: Licensing module of Orange Quantum Systems
Author-email: Orange Quantum Systems <info@orangeqs.com>
Project-URL: Documentation, https://products.orangeqs.info/licensing
Project-URL: Source, https://code.orangeqs.com/products/licensing
Project-URL: Issue tracker, https://code.orangeqs.com/products/licensing/-/issues
Project-URL: Changelog, https://code.orangeqs.com/products/licensing/-/blob/main/CHANGELOG.md
Keywords: orange-quantum-systems,orangeqs,oqs-licensing
Classifier: Development Status :: 4 - Beta
Classifier: Intended Audience :: Developers
Classifier: Intended Audience :: Science/Research
Classifier: License :: Other/Proprietary License
Classifier: Natural Language :: English
Classifier: Programming Language :: Python :: 3
Classifier: Programming Language :: Python :: 3.9
Classifier: Programming Language :: Python :: 3.10
Classifier: Programming Language :: Python :: 3.11
Classifier: Programming Language :: Python :: 3.12
Requires-Python: >=3.9
Requires-Dist: cryptography
Requires-Dist: pynacl
Requires-Dist: py-machineid
Requires-Dist: requests
Provides-Extra: dev
Requires-Dist: oqs-licensing[docs,test]; extra == "dev"
Requires-Dist: black; extra == "dev"
Requires-Dist: coverage; extra == "dev"
Requires-Dist: pygments; extra == "dev"
Requires-Dist: pre-commit; extra == "dev"
Requires-Dist: pre-commit-hooks; extra == "dev"
Requires-Dist: ruff; extra == "dev"
Requires-Dist: pyright; extra == "dev"
Requires-Dist: pytest-cov; extra == "dev"
Provides-Extra: docs
Requires-Dist: sphinx>=5.1.1; extra == "docs"
Requires-Dist: pydata-sphinx-theme; extra == "docs"
Requires-Dist: myst-nb; extra == "docs"
Requires-Dist: jupyter-cache; extra == "docs"
Requires-Dist: sphinx-autodoc-typehints; extra == "docs"
Requires-Dist: sphinx-togglebutton; extra == "docs"
Requires-Dist: sphinxcontrib-bibtex; extra == "docs"
Requires-Dist: sphinx-design; extra == "docs"
Requires-Dist: sphinx-copybutton; extra == "docs"
Requires-Dist: scanpydoc; extra == "docs"
Requires-Dist: docutils<0.18; extra == "docs"
Provides-Extra: test
Requires-Dist: pytest; extra == "test"
